[
  { "id": "d1", "url": "https://6a2b1ca89e041c30a185a1ae.imgix.net/images/tiktokio.com1781157543_7RLItspo4JeULfEYUdhG.jpg" },
  { "id": "d2", "url": "https://6a2b1ca89e041c30a185a1ae.imgix.net/images/tiktokio.com1781157543_eXN8pKrkh7RS9clabqmO.jpg" },
  { "id": "d3", "url": "https://6a2b1ca89e041c30a185a1ae.imgix.net/images/tiktokio.com1781157543_Utx3qAjrSJcTTT22GmAF.jpg" },
  { "id": "d4", "url": "https://6a2b1ca89e041c30a185a1ae.imgix.net/images/tiktokio.com1781157543_AgD2g2YTEcQ7ojXgrVqC.jpg" },
  { "id": "d5", "url": "https://6a2b1ca89e041c30a185a1ae.imgix.net/images/tiktokio.com1781157680_I9h5RHJwc7ILuo0i9gdd.jpg" },
  { "id": "d6", "url": "https://6a2b1ca89e041c30a185a1ae.imgix.net/images/tiktokio.com1781157543_IEfWSMGPOMCibSoy5YwX.jpg" },
  { "id": "d7", "url": "https://6a2b1ca89e041c30a185a1ae.imgix.net/images/tiktokio.com1781157680_tY1psrfceLfLnLGrrnMO.jpg" },
  { "id": "d8", "url": "https://6a2b1ca89e041c30a185a1ae.imgix.net/images/tiktokio.com1781157680_RmuwWqWZJ3lRPJ3ykQxR.jpg" },
  { "id": "d9", "url": "https://6a2b1ca89e041c30a185a1ae.imgix.net/images/tiktokio.com1781157680_xtdYdkKu53LegpEiIZuw.jpg" },
  { "id": "d10", "url": "https://6a2b1ca89e041c30a185a1ae.imgix.net/images/tiktokio.com1781157737_k4hqQePA3e7T1izssQ1k.jpg" },
  { "id": "d11", "url": "https://6a2b1ca89e041c30a185a1ae.imgix.net/images/tiktokio.com1781157737_FStQm9lvjCYQmHDLetX0.jpg" },
  { "id": "d12", "url": "https://6a2b1ca89e041c30a185a1ae.imgix.net/images/tiktokio.com1781157737_2fxHvUKPaXmLbYDYinEf.jpg" },
  { "id": "d13", "url": "https://6a2b1ca89e041c30a185a1ae.imgix.net/images/tiktokio.com1781157737_hD8j2EtVPJ5fI2NW74CZ.jpg" },
  { "id": "d14", "url": "https://6a2b1ca89e041c30a185a1ae.imgix.net/images/tiktokio.com1781157737_W7V6yLwyrSvzSL8zae8U.jpg" }
]
